{
"Class" : "weka.filters.unsupervised.instance.RemovePercentage", 
"Methods" : [{ "Name" : "setOptions" ,
"Edges" : 8,
"Duas" : 11,
"2" : 0, 
 "3" : 1, 
 "8" : 6, 
 "9" : 7},{ "Name" : "getOptions" ,
"Edges" : 4,
"Duas" : 4,
"0" : 1, 
 "1" : 2},{ "Name" : "setPercentage" ,
"Edges" : 6,
"Duas" : 6,
"1" : 2, 
 "2" : 3, 
 "3" : 0, 
 "4" : 1},{ "Name" : "input" ,
"Edges" : 10,
"Duas" : 14,
"0" : 4, 
 "1" : 5, 
 "2" : 8, 
 "3" : 9, 
 "4" : 2, 
 "5" : 3, 
 "12" : 8, 
 "13" : 9},{ "Name" : "batchFinished" ,
"Edges" : 19,
"Duas" : 39,
"0" : 8, 
 "1" : 9, 
 "4" : 4, 
 "5" : 5, 
 "9" : 6, 
 "10" : 7, 
 "14" : 4, 
 "15" : 5, 
 "16" : 11, 
 "17" : 12, 
 "21" : 13, 
 "22" : 14, 
 "23" : 13, 
 "24" : 14, 
 "27" : 13, 
 "28" : 14, 
 "31" : 11, 
 "32" : 12, 
 "35" : 11, 
 "36" : 12}]
}