{
"Class" : "weka.core.converters.LibSVMLoader", 
"Methods" : [{ "Name" : "reset" ,
"Edges" : 11,
"0" : [ 2,7 ],
"1" : [ 1,3 ],
"2" : [ 1,2 ],
"3" : [ 0,5 ],
"4" : [ 0,1 ],
"5" : [ 5,6 ],
"6" : [ 5,1 ],
"7" : [ 4,2 ],
"8" : [ 3,4 ],
"9" : [ 3,2 ],
"10" : [ 6,2 ]
},{ "Name" : "libsvmToArray" ,
"Edges" : 11,
"0" : [ 0,1 ],
"1" : [ 3,5 ],
"2" : [ 3,4 ],
"3" : [ 5,3 ],
"4" : [ 2,3 ],
"5" : [ 6,7 ],
"6" : [ 6,1 ],
"7" : [ 7,1 ],
"8" : [ 1,6 ],
"9" : [ 1,2 ],
"10" : [ 4,8 ]
},{ "Name" : "determineNumAttributes" ,
"Edges" : 4,
"0" : [ 2,1 ],
"1" : [ 1,3 ],
"2" : [ 0,2 ],
"3" : [ 0,1 ]
},{ "Name" : "getStructure" ,
"Edges" : 43,
"0" : [ 17,23 ],
"1" : [ 17,18 ],
"2" : [ 20,22 ],
"3" : [ 20,21 ],
"4" : [ 11,10 ],
"5" : [ 16,24 ],
"6" : [ 16,17 ],
"7" : [ 6,7 ],
"8" : [ 2,30 ],
"9" : [ 5,13 ],
"10" : [ 5,6 ],
"11" : [ 25,26 ],
"12" : [ 25,17 ],
"13" : [ 4,15 ],
"14" : [ 4,5 ],
"15" : [ 18,19 ],
"16" : [ 24,27 ],
"17" : [ 24,25 ],
"18" : [ 0,29 ],
"19" : [ 0,1 ],
"20" : [ 15,28 ],
"21" : [ 15,16 ],
"22" : [ 12,7 ],
"23" : [ 21,4 ],
"24" : [ 3,4 ],
"25" : [ 19,20 ],
"26" : [ 10,2 ],
"27" : [ 23,19 ],
"28" : [ 7,12 ],
"29" : [ 7,8 ],
"30" : [ 26,17 ],
"31" : [ 27,17 ],
"32" : [ 13,14 ],
"33" : [ 13,6 ],
"34" : [ 14,6 ],
"35" : [ 29,30 ],
"36" : [ 8,11 ],
"37" : [ 8,9 ],
"38" : [ 1,3 ],
"39" : [ 1,2 ],
"40" : [ 9,10 ],
"41" : [ 22,20 ],
"42" : [ 28,16 ]
},{ "Name" : "getDataSet" ,
"Edges" : 18,
"0" : [ 1,11 ],
"1" : [ 1,2 ],
"2" : [ 2,10 ],
"3" : [ 2,3 ],
"4" : [ 6,9 ],
"5" : [ 6,7 ],
"6" : [ 12,13 ],
"7" : [ 0,12 ],
"8" : [ 0,1 ],
"9" : [ 3,4 ],
"10" : [ 10,3 ],
"11" : [ 11,13 ],
"12" : [ 7,8 ],
"13" : [ 9,8 ],
"14" : [ 4,6 ],
"15" : [ 4,5 ],
"16" : [ 8,4 ],
"17" : [ 5,13 ]
}]
}