{
"Class" : "weka.core.InstanceComparator", 
"Methods" : [{ "Name" : "compare" ,
"Edges" : 52,
"0" : [ 4,34 ],
"1" : [ 6,30 ],
"2" : [ 6,7 ],
"3" : [ 28,19 ],
"4" : [ 0,33 ],
"5" : [ 0,1 ],
"6" : [ 5,32 ],
"7" : [ 5,6 ],
"8" : [ 12,13 ],
"9" : [ 12,9 ],
"10" : [ 17,18 ],
"11" : [ 20,4 ],
"12" : [ 30,31 ],
"13" : [ 30,7 ],
"14" : [ 25,29 ],
"15" : [ 25,26 ],
"16" : [ 24,19 ],
"17" : [ 26,28 ],
"18" : [ 26,27 ],
"19" : [ 15,8 ],
"20" : [ 15,16 ],
"21" : [ 33,2 ],
"22" : [ 10,4 ],
"23" : [ 27,19 ],
"24" : [ 13,14 ],
"25" : [ 2,3 ],
"26" : [ 8,12 ],
"27" : [ 8,9 ],
"28" : [ 32,14 ],
"29" : [ 18,21 ],
"30" : [ 18,19 ],
"31" : [ 3,5 ],
"32" : [ 3,4 ],
"33" : [ 7,15 ],
"34" : [ 7,8 ],
"35" : [ 11,4 ],
"36" : [ 1,2 ],
"37" : [ 16,25 ],
"38" : [ 16,24 ],
"39" : [ 16,17 ],
"40" : [ 9,11 ],
"41" : [ 9,10 ],
"42" : [ 22,23 ],
"43" : [ 22,19 ],
"44" : [ 23,18 ],
"45" : [ 31,14 ],
"46" : [ 21,22 ],
"47" : [ 21,19 ],
"48" : [ 29,14 ],
"49" : [ 14,3 ],
"50" : [ 19,20 ],
"51" : [ 19,14 ]
},{ "Name" : "main" ,
"Edges" : 4,
"0" : [ 2,3 ],
"1" : [ 1,3 ],
"2" : [ 0,2 ],
"3" : [ 0,1 ]
}]
}