{
"Class" : "org.jfree.chart.renderer.category.LevelRenderer", 
"Methods" : [{ "Name" : "calculateItemWidth" ,
"Duas" : 48,
"0" :  "(206,219, this)",
"1" :  "(206,226, this)",
"2" :  "(206,212, plot)",
"3" :  "(206,217, dataArea)",
"4" :  "(206,214, dataArea)",
"5" :  "(206,(207,208), dataset)",
"6" :  "(206,(207,238), dataset)",
"7" :  "(206,208, dataset)",
"8" :  "(206,209, dataset)",
"9" :  "(206,(209,209), state)",
"10" :  "(206,(209,209), state)",
"11" :  "(206,209, state)",
"12" :  "(206,235, state)",
"13" :  "(206,232, state)",
"14" :  "(206,(213,214), HORIZONTAL)",
"15" :  "(206,(213,216), HORIZONTAL)",
"16" :  "(206,(216,217), VERTICAL)",
"17" :  "(206,(216,219), VERTICAL)",
"18" :  "(206,228, domainAxis)",
"19" :  "(206,223, domainAxis)",
"20" :  "(208,(222,223), columns)",
"21" :  "(208,(222,225), columns)",
"22" :  "(208,(231,232), columns)",
"23" :  "(208,(231,235), columns)",
"24" :  "(208,232, columns)",
"25" :  "(209,(225,226), rows)",
"26" :  "(209,(225,228), rows)",
"27" :  "(209,(231,232), rows)",
"28" :  "(209,(231,235), rows)",
"29" :  "(209,232, rows)",
"30" :  "(211,219, space)",
"31" :  "(211,228, space)",
"32" :  "(212,(213,214), orientation)",
"33" :  "(212,(213,216), orientation)",
"34" :  "(212,(216,217), orientation)",
"35" :  "(212,(216,219), orientation)",
"36" :  "(214,219, space)",
"37" :  "(214,228, space)",
"38" :  "(217,219, space)",
"39" :  "(217,228, space)",
"40" :  "(219,235, maxWidth)",
"41" :  "(219,232, maxWidth)",
"42" :  "(220,228, categoryMargin)",
"43" :  "(221,228, currentItemMargin)",
"44" :  "(223,228, categoryMargin)",
"45" :  "(226,228, currentItemMargin)",
"46" :  "(228,235, used)",
"47" :  "(228,232, used)"},{ "Name" : "calculateBarW0" ,
"Duas" : 44,
"0" :  "(263,270, this)",
"1" :  "(263,276, this)",
"2" :  "(263,286, this)",
"3" :  "(263,278, this)",
"4" :  "(263,280, this)",
"5" :  "(263,274, this)",
"6" :  "(263,270, plot)",
"7" :  "(263,286, plot)",
"8" :  "(263,(264,265), orientation)",
"9" :  "(263,(264,268), orientation)",
"10" :  "(263,268, dataArea)",
"11" :  "(263,270, dataArea)",
"12" :  "(263,286, dataArea)",
"13" :  "(263,265, dataArea)",
"14" :  "(263,270, domainAxis)",
"15" :  "(263,286, domainAxis)",
"16" :  "(263,280, domainAxis)",
"17" :  "(263,272, state)",
"18" :  "(263,286, state)",
"19" :  "(263,282, state)",
"20" :  "(263,282, row)",
"21" :  "(263,270, column)",
"22" :  "(263,286, column)",
"23" :  "(263,(264,265), HORIZONTAL)",
"24" :  "(263,(264,268), HORIZONTAL)",
"25" :  "(265,278, space)",
"26" :  "(265,280, space)",
"27" :  "(268,278, space)",
"28" :  "(268,280, space)",
"29" :  "(270,282, barW0)",
"30" :  "(272,(273,274), seriesCount)",
"31" :  "(272,(273,276), seriesCount)",
"32" :  "(272,(277,278), seriesCount)",
"33" :  "(272,(277,286), seriesCount)",
"34" :  "(272,278, seriesCount)",
"35" :  "(272,280, seriesCount)",
"36" :  "(274,(277,278), seriesCount)",
"37" :  "(274,(277,286), seriesCount)",
"38" :  "(274,278, seriesCount)",
"39" :  "(274,280, seriesCount)",
"40" :  "(276,278, categoryCount)",
"41" :  "(276,280, categoryCount)",
"42" :  "(282,290, barW0)",
"43" :  "(286,290, barW0)"},{ "Name" : "drawItem" ,
"Duas" : 97,
"0" :  "(315,329, this)",
"1" :  "(315,350, this)",
"2" :  "(315,351, this)",
"3" :  "(315,356, this)",
"4" :  "(315,365, this)",
"5" :  "(315,372, this)",
"6" :  "(315,(358,359), this)",
"7" :  "(315,(358,364), this)",
"8" :  "(315,359, this)",
"9" :  "(315,352, g2)",
"10" :  "(315,353, g2)",
"11" :  "(315,354, g2)",
"12" :  "(315,359, g2)",
"13" :  "(315,329, state)",
"14" :  "(315,345, state)",
"15" :  "(315,347, state)",
"16" :  "(315,365, state)",
"17" :  "(315,370, state)",
"18" :  "(315,340, state)",
"19" :  "(315,341, state)",
"20" :  "(315,329, dataArea)",
"21" :  "(315,332, dataArea)",
"22" :  "(315,328, plot)",
"23" :  "(315,329, plot)",
"24" :  "(315,331, plot)",
"25" :  "(315,364, plot)",
"26" :  "(315,329, domainAxis)",
"27" :  "(315,332, rangeAxis)",
"28" :  "(315,321, dataset)",
"29" :  "(315,364, dataset)",
"30" :  "(315,365, dataset)",
"31" :  "(315,372, dataset)",
"32" :  "(315,359, dataset)",
"33" :  "(315,321, row)",
"34" :  "(315,350, row)",
"35" :  "(315,351, row)",
"36" :  "(315,356, row)",
"37" :  "(315,365, row)",
"38" :  "(315,372, row)",
"39" :  "(315,(358,359), row)",
"40" :  "(315,(358,364), row)",
"41" :  "(315,359, row)",
"42" :  "(315,321, column)",
"43" :  "(315,329, column)",
"44" :  "(315,350, column)",
"45" :  "(315,351, column)",
"46" :  "(315,356, column)",
"47" :  "(315,365, column)",
"48" :  "(315,372, column)",
"49" :  "(315,(358,359), column)",
"50" :  "(315,(358,364), column)",
"51" :  "(315,359, column)",
"52" :  "(315,350, selected)",
"53" :  "(315,351, selected)",
"54" :  "(315,356, selected)",
"55" :  "(315,372, selected)",
"56" :  "(315,(358,359), selected)",
"57" :  "(315,(358,364), selected)",
"58" :  "(315,359, selected)",
"59" :  "(315,(338,339), HORIZONTAL)",
"60" :  "(315,(338,345), HORIZONTAL)",
"61" :  "(315,(316,317), visibleRow)",
"62" :  "(315,(316,321), visibleRow)",
"63" :  "(315,329, visibleRow)",
"64" :  "(321,(322,323), dataValue)",
"65" :  "(321,(322,326), dataValue)",
"66" :  "(321,326, dataValue)",
"67" :  "(326,365, value)",
"68" :  "(326,(359,359), value)",
"69" :  "(326,(359,359), value)",
"70" :  "(328,(338,339), orientation)",
"71" :  "(328,(338,345), orientation)",
"72" :  "(328,365, orientation)",
"73" :  "(328,359, orientation)",
"74" :  "(329,345, barW0)",
"75" :  "(329,347, barW0)",
"76" :  "(329,365, barW0)",
"77" :  "(329,340, barW0)",
"78" :  "(329,341, barW0)",
"79" :  "(332,346, barL)",
"80" :  "(332,347, barL)",
"81" :  "(332,365, barL)",
"82" :  "(332,339, barL)",
"83" :  "(332,341, barL)",
"84" :  "(339,359, x)",
"85" :  "(340,359, y)",
"86" :  "(341,354, line)",
"87" :  "(341,372, line)",
"88" :  "(345,359, x)",
"89" :  "(346,359, y)",
"90" :  "(347,354, line)",
"91" :  "(347,372, line)",
"92" :  "(356,(358,358), generator)",
"93" :  "(356,(358,364), generator)",
"94" :  "(370,(371,372), entities)",
"95" :  "(370,(371,376), entities)",
"96" :  "(370,372, entities)"},{ "Name" : "calculateSeriesWidth" ,
"Duas" : 9,
"0" :  "(390,395, space)",
"1" :  "(390,393, axis)",
"2" :  "(390,(392,393), categories)",
"3" :  "(390,(392,395), categories)",
"4" :  "(390,395, categories)",
"5" :  "(390,395, series)",
"6" :  "(390,395, factor)",
"7" :  "(390,393, factor)",
"8" :  "(393,395, factor)"},{ "Name" : "equals" ,
"Duas" : 25,
"0" :  "(427,(427,428), this)",
"1" :  "(427,(427,430), this)",
"2" :  "(427,(434,435), this)",
"3" :  "(427,(434,437), this)",
"4" :  "(427,(437,438), this)",
"5" :  "(427,(437,440), this)",
"6" :  "(427,440, this)",
"7" :  "(427,(427,428), obj)",
"8" :  "(427,(427,430), obj)",
"9" :  "(427,(430,431), obj)",
"10" :  "(427,(430,433), obj)",
"11" :  "(427,433, obj)",
"12" :  "(427,440, obj)",
"13" :  "(427,(434,435), this.itemMargin)",
"14" :  "(427,(434,437), this.itemMargin)",
"15" :  "(427,(437,438), this.maxItemWidth)",
"16" :  "(427,(437,440), this.maxItemWidth)",
"17" :  "(433,(434,435), that)",
"18" :  "(433,(434,437), that)",
"19" :  "(433,(437,438), that)",
"20" :  "(433,(437,440), that)",
"21" :  "(433,(434,435), that.itemMargin)",
"22" :  "(433,(434,437), that.itemMargin)",
"23" :  "(433,(437,438), that.maxItemWidth)",
"24" :  "(433,(437,440), that.maxItemWidth)"}]
}