{
"Class" : "org.jfree.data.xy.DefaultHighLowDataset", 
"Methods" : [{ "Name" : "<init>" ,
"Duas" : 20,
"0" :  "(106,114, this)",
"1" :  "(106,115, this)",
"2" :  "(106,116, this)",
"3" :  "(106,117, this)",
"4" :  "(106,118, this)",
"5" :  "(106,119, this)",
"6" :  "(106,120, this)",
"7" :  "(106,121, this)",
"8" :  "(106,123, this)",
"9" :  "(106,(108,109), seriesKey)",
"10" :  "(106,(108,111), seriesKey)",
"11" :  "(106,114, seriesKey)",
"12" :  "(106,(111,112), date)",
"13" :  "(106,(111,114), date)",
"14" :  "(106,115, date)",
"15" :  "(106,117, high)",
"16" :  "(106,118, low)",
"17" :  "(106,119, open)",
"18" :  "(106,120, close)",
"19" :  "(106,121, volume)"},{ "Name" : "getHighValue" ,
"Duas" : 5,
"0" :  "(215,220, result)",
"1" :  "(216,(217,218), n)",
"2" :  "(216,(217,220), n)",
"3" :  "(216,218, n)",
"4" :  "(218,220, result)"},{ "Name" : "getLowValue" ,
"Duas" : 5,
"0" :  "(249,254, result)",
"1" :  "(250,(251,252), low)",
"2" :  "(250,(251,254), low)",
"3" :  "(250,252, low)",
"4" :  "(252,254, result)"},{ "Name" : "getOpenValue" ,
"Duas" : 5,
"0" :  "(283,288, result)",
"1" :  "(284,(285,286), open)",
"2" :  "(284,(285,288), open)",
"3" :  "(284,286, open)",
"4" :  "(286,288, result)"},{ "Name" : "getCloseValue" ,
"Duas" : 5,
"0" :  "(317,322, result)",
"1" :  "(318,(319,320), close)",
"2" :  "(318,(319,322), close)",
"3" :  "(318,320, close)",
"4" :  "(320,322, result)"},{ "Name" : "getVolumeValue" ,
"Duas" : 5,
"0" :  "(351,356, result)",
"1" :  "(352,(353,354), volume)",
"2" :  "(352,(353,356), volume)",
"3" :  "(352,354, volume)",
"4" :  "(354,356, result)"},{ "Name" : "equals" ,
"Duas" : 63,
"0" :  "(389,(389,390), this)",
"1" :  "(389,(389,392), this)",
"2" :  "(389,(396,397), this)",
"3" :  "(389,(396,399), this)",
"4" :  "(389,(399,400), this)",
"5" :  "(389,(399,402), this)",
"6" :  "(389,(402,403), this)",
"7" :  "(389,(402,405), this)",
"8" :  "(389,(405,406), this)",
"9" :  "(389,(405,408), this)",
"10" :  "(389,(408,409), this)",
"11" :  "(389,(408,411), this)",
"12" :  "(389,(411,412), this)",
"13" :  "(389,(411,414), this)",
"14" :  "(389,(414,415), this)",
"15" :  "(389,(414,417), this)",
"16" :  "(389,(389,390), obj)",
"17" :  "(389,(389,392), obj)",
"18" :  "(389,(392,393), obj)",
"19" :  "(389,(392,395), obj)",
"20" :  "(389,395, obj)",
"21" :  "(389,(396,397), this.seriesKey)",
"22" :  "(389,(396,399), this.seriesKey)",
"23" :  "(389,(399,400), this.date)",
"24" :  "(389,(399,402), this.date)",
"25" :  "(389,(402,403), this.open)",
"26" :  "(389,(402,405), this.open)",
"27" :  "(389,(405,406), this.high)",
"28" :  "(389,(405,408), this.high)",
"29" :  "(389,(408,409), this.low)",
"30" :  "(389,(408,411), this.low)",
"31" :  "(389,(411,412), this.close)",
"32" :  "(389,(411,414), this.close)",
"33" :  "(389,(414,415), this.volume)",
"34" :  "(389,(414,417), this.volume)",
"35" :  "(395,(396,397), that)",
"36" :  "(395,(396,399), that)",
"37" :  "(395,(399,400), that)",
"38" :  "(395,(399,402), that)",
"39" :  "(395,(402,403), that)",
"40" :  "(395,(402,405), that)",
"41" :  "(395,(405,406), that)",
"42" :  "(395,(405,408), that)",
"43" :  "(395,(408,409), that)",
"44" :  "(395,(408,411), that)",
"45" :  "(395,(411,412), that)",
"46" :  "(395,(411,414), that)",
"47" :  "(395,(414,415), that)",
"48" :  "(395,(414,417), that)",
"49" :  "(395,(396,397), that.seriesKey)",
"50" :  "(395,(396,399), that.seriesKey)",
"51" :  "(395,(399,400), that.date)",
"52" :  "(395,(399,402), that.date)",
"53" :  "(395,(402,403), that.open)",
"54" :  "(395,(402,405), that.open)",
"55" :  "(395,(405,406), that.high)",
"56" :  "(395,(405,408), that.high)",
"57" :  "(395,(408,409), that.low)",
"58" :  "(395,(408,411), that.low)",
"59" :  "(395,(411,412), that.close)",
"60" :  "(395,(411,414), that.close)",
"61" :  "(395,(414,415), that.volume)",
"62" :  "(395,(414,417), that.volume)"},{ "Name" : "createNumberArray" ,
"Duas" : 15,
"0" :  "(429,(430,431), data)",
"1" :  "(429,(430,433), data)",
"2" :  "(429,431, data)",
"3" :  "(429,433, result)",
"4" :  "(429,431, result)",
"5" :  "(430,(430,431), i)",
"6" :  "(430,(430,433), i)",
"7" :  "(430,431, i)",
"8" :  "(430,431, i)",
"9" :  "(430,430, i)",
"10" :  "(430,(430,431), i)",
"11" :  "(430,(430,433), i)",
"12" :  "(430,431, i)",
"13" :  "(430,431, i)",
"14" :  "(430,430, i)"},{ "Name" : "setSelected" ,
"Duas" : 10,
"0" :  "(446,449, this)",
"1" :  "(446,451, this)",
"2" :  "(446,(446,447), series)",
"3" :  "(446,(446,449), series)",
"4" :  "(446,447, series)",
"5" :  "(446,449, item)",
"6" :  "(446,449, selected)",
"7" :  "(446,(450,451), notify)",
"8" :  "(446,(450,453), notify)",
"9" :  "(446,449, this.selected)"}]
}