{
"Class" : "org.jfree.chart.plot.junit.ValueMarkerTests", 
"Methods" : [{ "Name" : "suite" ,
"Duas" : 4,
"0" :  "(90,(90,90), class$org$jfree$chart$plot$junit$ValueMarkerTests)",
"1" :  "(90,(90,90), class$org$jfree$chart$plot$junit$ValueMarkerTests)",
"2" :  "(90,90, class$org$jfree$chart$plot$junit$ValueMarkerTests)",
"3" :  "(90,90, class$org$jfree$chart$plot$junit$ValueMarkerTests)"},{ "Name" : "testCloning" ,
"Duas" : 10,
"0" :  "(191,(199,199), m1)",
"1" :  "(191,(199,199), m1)",
"2" :  "(191,(200,200), m1)",
"3" :  "(191,(200,200), m1)",
"4" :  "(191,201, m1)",
"5" :  "(194,(199,199), m2)",
"6" :  "(194,(199,199), m2)",
"7" :  "(194,(200,200), m2)",
"8" :  "(194,(200,200), m2)",
"9" :  "(194,201, m2)"}]
}