{
"Class" : "org.jfree.chart.plot.junit.CombinedRangeXYPlotTests", 
"Methods" : [{ "Name" : "suite" ,
"Duas" : 4,
"0" :  "(99,(99,99), class$org$jfree$chart$plot$junit$CombinedRangeXYPlotTests)",
"1" :  "(99,(99,99), class$org$jfree$chart$plot$junit$CombinedRangeXYPlotTests)",
"2" :  "(99,99, class$org$jfree$chart$plot$junit$CombinedRangeXYPlotTests)",
"3" :  "(99,99, class$org$jfree$chart$plot$junit$CombinedRangeXYPlotTests)"},{ "Name" : "testRemoveSubplot" ,
"Duas" : 4,
"0" :  "(126,(133,133), plot1)",
"1" :  "(126,(133,133), plot1)",
"2" :  "(132,(133,133), plots)",
"3" :  "(132,(133,133), plots)"},{ "Name" : "testCloning" ,
"Duas" : 10,
"0" :  "(140,(148,148), plot1)",
"1" :  "(140,(148,148), plot1)",
"2" :  "(140,(149,149), plot1)",
"3" :  "(140,(149,149), plot1)",
"4" :  "(140,150, plot1)",
"5" :  "(143,(148,148), plot2)",
"6" :  "(143,(148,148), plot2)",
"7" :  "(143,(149,149), plot2)",
"8" :  "(143,(149,149), plot2)",
"9" :  "(143,150, plot2)"},{ "Name" : "testNotification" ,
"Duas" : 10,
"0" :  "(181,187, this)",
"1" :  "(181,193, this)",
"2" :  "(181,195, this)",
"3" :  "(181,187, this.events)",
"4" :  "(181,193, this.events)",
"5" :  "(181,195, this.events)",
"6" :  "(182,194, chart)",
"7" :  "(185,(186,186), xAxis)",
"8" :  "(185,(186,186), xAxis)",
"9" :  "(185,186, xAxis)"}]
}