{
"Class" : "elki.clustering.CFSFDP", 
"Methods" : [{ "Name" : "run" ,
"Duas" : 134,
"0" :  "(123,146, this)",
"1" :  "(123,158, this)",
"2" :  "(123,131, this)",
"3" :  "(123,(132,132), this)",
"4" :  "(123,(132,133), this)",
"5" :  "(123,(132,133), this)",
"6" :  "(123,(132,131), this)",
"7" :  "(123,142, FACTORY)",
"8" :  "(123,143, FACTORY)",
"9" :  "(123,167, FACTORY)",
"10" :  "(123,(128,128), LOG)",
"11" :  "(123,(128,128), LOG)",
"12" :  "(123,139, LOG)",
"13" :  "(123,(144,144), LOG)",
"14" :  "(123,(144,144), LOG)",
"15" :  "(123,161, LOG)",
"16" :  "(123,(169,169), LOG)",
"17" :  "(123,(169,169), LOG)",
"18" :  "(123,181, LOG)",
"19" :  "(123,179, LOG)",
"20" :  "(123,169, LOG)",
"21" :  "(123,159, LOG)",
"22" :  "(123,144, LOG)",
"23" :  "(123,137, LOG)",
"24" :  "(123,128, LOG)",
"25" :  "(123,131, this.dc)",
"26" :  "(123,(132,132), this.dc)",
"27" :  "(123,(132,133), this.dc)",
"28" :  "(123,(132,133), this.dc)",
"29" :  "(123,(132,131), this.dc)",
"30" :  "(123,146, this.k)",
"31" :  "(123,158, this.k)",
"32" :  "(123,151, searcher)",
"33" :  "(123,(151,152), searcher)",
"34" :  "(123,(151,156), searcher)",
"35" :  "(123,(152,152), searcher)",
"36" :  "(123,(152,151), searcher)",
"37" :  "(123,151, searcher)",
"38" :  "(123,152, searcher)",
"39" :  "(123,(152,153), searcher)",
"40" :  "(123,(152,151), searcher)",
"41" :  "(123,153, searcher)",
"42" :  "(123,131, searcher)",
"43" :  "(123,(131,132), searcher)",
"44" :  "(123,(131,136), searcher)",
"45" :  "(123,(132,132), searcher)",
"46" :  "(123,(132,133), searcher)",
"47" :  "(123,131, searcher)",
"48" :  "(123,(132,133), searcher)",
"49" :  "(123,(132,131), searcher)",
"50" :  "(126,129, ids)",
"51" :  "(126,142, ids)",
"52" :  "(126,143, ids)",
"53" :  "(126,147, ids)",
"54" :  "(126,165, ids)",
"55" :  "(126,167, ids)",
"56" :  "(126,169, ids)",
"57" :  "(126,144, ids)",
"58" :  "(126,128, ids)",
"59" :  "(127,166, density)",
"60" :  "(127,171, density)",
"61" :  "(127,148, density)",
"62" :  "(127,(152,152), density)",
"63" :  "(127,(152,151), density)",
"64" :  "(127,136, density)",
"65" :  "(128,139, prog)",
"66" :  "(128,137, prog)",
"67" :  "(129,(129,130), it)",
"68" :  "(129,(129,139), it)",
"69" :  "(129,131, it)",
"70" :  "(129,136, it)",
"71" :  "(129,129, it)",
"72" :  "(130,136, found)",
"73" :  "(130,133, found)",
"74" :  "(133,136, found)",
"75" :  "(133,133, found)",
"76" :  "(142,171, nextdist)",
"77" :  "(142,156, nextdist)",
"78" :  "(143,172, nextn)",
"79" :  "(143,157, nextn)",
"80" :  "(144,161, nprog)",
"81" :  "(144,159, nprog)",
"82" :  "(145,172, tmp)",
"83" :  "(145,150, tmp)",
"84" :  "(145,157, tmp)",
"85" :  "(145,153, tmp)",
"86" :  "(146,163, heap)",
"87" :  "(146,158, heap)",
"88" :  "(147,(147,148), it)",
"89" :  "(147,(147,161), it)",
"90" :  "(147,148, it)",
"91" :  "(147,151, it)",
"92" :  "(147,156, it)",
"93" :  "(147,157, it)",
"94" :  "(147,147, it)",
"95" :  "(148,158, dens)",
"96" :  "(148,(152,152), dens)",
"97" :  "(148,(152,151), dens)",
"98" :  "(149,156, dist)",
"99" :  "(149,158, dist)",
"100" :  "(149,(152,153), dist)",
"101" :  "(149,(152,151), dist)",
"102" :  "(152,153, d)",
"103" :  "(152,153, d)",
"104" :  "(153,156, dist)",
"105" :  "(153,158, dist)",
"106" :  "(153,(152,153), dist)",
"107" :  "(153,(152,151), dist)",
"108" :  "(163,(172,172), gammathreshold)",
"109" :  "(163,(172,172), gammathreshold)",
"110" :  "(165,170, sorted)",
"111" :  "(167,172, cluster)",
"112" :  "(167,178, cluster)",
"113" :  "(168,182, clustering)",
"114" :  "(168,183, clustering)",
"115" :  "(168,174, clustering)",
"116" :  "(169,181, cprog)",
"117" :  "(169,179, cprog)",
"118" :  "(170,(170,171), it)",
"119" :  "(170,(170,181), it)",
"120" :  "(170,171, it)",
"121" :  "(170,172, it)",
"122" :  "(170,177, it)",
"123" :  "(170,178, it)",
"124" :  "(170,170, it)",
"125" :  "(170,175, it)",
"126" :  "(171,(172,172), gamma)",
"127" :  "(171,(172,172), gamma)",
"128" :  "(172,(173,174), c)",
"129" :  "(172,(173,177), c)",
"130" :  "(172,177, c)",
"131" :  "(172,178, c)",
"132" :  "(174,177, c)",
"133" :  "(174,178, c)"}]
}