{
"Class" : "com.google.javascript.jscomp.SourceMap", 
"Methods" : [{ "Name" : "addMapping" ,
"Duas" : 24,
"0" :  "(121,130, this)",
"1" :  "(121,(139,139), this)",
"2" :  "(121,(139,141), this)",
"3" :  "(121,144, this)",
"4" :  "(121,(139,141), this)",
"5" :  "(121,(139,144), this)",
"6" :  "(121,(126,127), node)",
"7" :  "(121,(126,130), node)",
"8" :  "(121,132, node)",
"9" :  "(121,144, node)",
"10" :  "(121,144, outputStartPosition)",
"11" :  "(121,144, outputEndPosition)",
"12" :  "(121,(139,139), this.generator)",
"13" :  "(121,(139,141), this.generator)",
"14" :  "(121,144, this.generator)",
"15" :  "(121,(139,141), this.generator)",
"16" :  "(121,(139,144), this.generator)",
"17" :  "(121,(126,126), sourceFile)",
"18" :  "(121,(126,127), sourceFile)",
"19" :  "(121,130, sourceFile)",
"20" :  "(130,144, sourceFile)",
"21" :  "(132,144, originalName)",
"22" :  "(138,144, lineBaseOffset)",
"23" :  "(141,144, lineBaseOffset)"},{ "Name" : "fixupSourceLocation" ,
"Duas" : 40,
"0" :  "(155,(155,156), this)",
"1" :  "(155,(155,159), this)",
"2" :  "(155,159, this)",
"3" :  "(155,165, this)",
"4" :  "(155,178, this)",
"5" :  "(155,159, sourceFile)",
"6" :  "(155,178, sourceFile)",
"7" :  "(155,175, sourceFile)",
"8" :  "(155,(166,167), sourceFile)",
"9" :  "(155,(166,171), sourceFile)",
"10" :  "(155,167, sourceFile)",
"11" :  "(155,156, sourceFile)",
"12" :  "(155,(155,156), this.prefixMappings)",
"13" :  "(155,(155,159), this.prefixMappings)",
"14" :  "(155,165, this.prefixMappings)",
"15" :  "(155,159, this.sourceLocationFixupCache)",
"16" :  "(155,178, this.sourceLocationFixupCache)",
"17" :  "(159,(160,161), fixed)",
"18" :  "(159,(160,165), fixed)",
"19" :  "(159,(174,175), fixed)",
"20" :  "(159,(174,178), fixed)",
"21" :  "(159,178, fixed)",
"22" :  "(159,179, fixed)",
"23" :  "(159,161, fixed)",
"24" :  "(165,(165,165), i$)",
"25" :  "(165,(165,174), i$)",
"26" :  "(165,165, i$)",
"27" :  "(165,(166,167), mapping)",
"28" :  "(165,(166,171), mapping)",
"29" :  "(165,167, mapping)",
"30" :  "(165,(166,167), mapping.prefix)",
"31" :  "(165,(166,171), mapping.prefix)",
"32" :  "(165,167, mapping.prefix)",
"33" :  "(165,167, mapping.replacement)",
"34" :  "(167,(174,175), fixed)",
"35" :  "(167,(174,178), fixed)",
"36" :  "(167,178, fixed)",
"37" :  "(167,179, fixed)",
"38" :  "(175,178, fixed)",
"39" :  "(175,179, fixed)"}]
}