{
"Class" : "com.google.javascript.jscomp.SpecializeModule$SpecializationState", 
"Methods" : [{ "Name" : "reportSpecializedFunction" ,
"Nodes" : 4,
"Duas" : 7,
"0" :  [ 0,2 ],
"1" :  [ 0,1 ],
"2" :  [ 0,2 ],
"3" :  [ 0,2 ],
"4" :  [ 0,1 ],
"5" :  [ 0,2 ],
"6" :  [ 0,1 ]},{ "Name" : "reportSpecializedFunctionContainingNode" ,
"Nodes" : 4,
"Duas" : 4,
"0" :  [ 0,2 ],
"1" :  [ 0,2 ],
"2" :  [ 0,1 ],
"3" :  [ 0,2 ]},{ "Name" : "reportRemovedFunction" ,
"Nodes" : 4,
"Duas" : 11,
"0" :  [ 0,2 ],
"1" :  [ 0,1 ],
"2" :  [ 0,2 ],
"3" :  [ 0,2 ],
"4" :  [ 0,2 ],
"5" :  [ 0,1 ],
"6" :  [ 0,2 ],
"7" :  [ 0,2 ],
"8" :  [ 0,2 ],
"9" :  [ 0,1 ],
"10" :  [ 0,2 ]},{ "Name" : "canFixupFunction" ,
"Nodes" : 13,
"Duas" : 23,
"0" :  [ 0,2 ],
"1" :  [ 0,1 ],
"2" :  [ 0,2,1 ],
"3" :  [ 0,2,3 ],
"4" :  [ 0,2 ],
"5" :  [ 0,1 ],
"6" :  [ 0,2,1 ],
"7" :  [ 0,2,3 ],
"8" :  [ 0,3,11 ],
"9" :  [ 0,3,4 ],
"10" :  [ 0,4 ],
"11" :  [ 0,7,8 ],
"12" :  [ 0,7,6 ],
"13" :  [ 0,2,1 ],
"14" :  [ 0,2,3 ],
"15" :  [ 4,9 ],
"16" :  [ 4,5 ],
"17" :  [ 4,7,8 ],
"18" :  [ 4,7,6 ],
"19" :  [ 4,5,7 ],
"20" :  [ 4,5,6 ],
"21" :  [ 4,9,10 ],
"22" :  [ 4,9,5 ]},{ "Name" : "canFixupSpecializedFunctionContainingNode" ,
"Nodes" : 4,
"Duas" : 4,
"0" :  [ 0,2 ],
"1" :  [ 0,2 ],
"2" :  [ 0,1 ],
"3" :  [ 0,2 ]},{ "Name" : "nodeIsInGlobalScope" ,
"Nodes" : 5,
"Duas" : 4,
"0" :  [ 0,3 ],
"1" :  [ 0,1 ],
"2" :  [ 0,3 ],
"3" :  [ 0,1 ]},{ "Name" : "containingFunction" ,
"Nodes" : 7,
"Duas" : 6,
"0" :  [ 0,1,3 ],
"1" :  [ 0,1,2 ],
"2" :  [ 0,3 ],
"3" :  [ 3,5 ],
"4" :  [ 3,4 ],
"5" :  [ 3,5 ]}]
}