{
"Class" : "com.google.javascript.jscomp.InlineProperties$GatherCandidates", 
"Methods" : [{ "Name" : "visit" ,
"Edges" : 29,
"Duas" : 47,
"1" : 8, 
 "2" : 9, 
 "3" : 4, 
 "4" : 5, 
 "5" : 2, 
 "6" : 3, 
 "7" : 8, 
 "8" : 9, 
 "9" : 25, 
 "10" : 26, 
 "11" : 12, 
 "12" : 13, 
 "15" : 16, 
 "16" : 17, 
 "17" : 8, 
 "18" : 9, 
 "19" : 10, 
 "20" : 11, 
 "21" : 18, 
 "22" : 19, 
 "23" : 8, 
 "24" : 9, 
 "25" : 22, 
 "26" : 23, 
 "31" : 22, 
 "32" : 23, 
 "33" : 22, 
 "34" : 23, 
 "35" : 22, 
 "36" : 23, 
 "37" : 22, 
 "38" : 23, 
 "39" : 22, 
 "40" : 23, 
 "43" : 22, 
 "44" : 23, 
 "45" : 22, 
 "46" : 23},{ "Name" : "maybeCandidateDefinition" ,
"Edges" : 21,
"Duas" : 35,
"2" : 5, 
 "3" : 6, 
 "5" : 11, 
 "6" : 12, 
 "7" : 5, 
 "8" : 6, 
 "9" : 7, 
 "10" : 8, 
 "14" : 19, 
 "15" : 20, 
 "18" : 3, 
 "19" : 4, 
 "20" : 9, 
 "21" : 10, 
 "22" : 13, 
 "23" : 14, 
 "31" : 0, 
 "32" : 1},{ "Name" : "maybeGetInstanceTypeFromPrototypeRef" ,
"Edges" : 6,
"Duas" : 5,
"0" : 2, 
 "1" : 3, 
 "2" : 0, 
 "3" : 1},{ "Name" : "maybeStoreCandidateValue" ,
"Edges" : 10,
"Duas" : 21,
"0" : 1, 
 "1" : 2, 
 "2" : 3, 
 "3" : 4, 
 "5" : 3, 
 "6" : 4, 
 "8" : 1, 
 "9" : 2, 
 "11" : 5, 
 "12" : 6, 
 "13" : 7, 
 "14" : 8, 
 "16" : 1, 
 "17" : 2, 
 "18" : 3, 
 "19" : 4},{ "Name" : "inContructor" ,
"Edges" : 7,
"Duas" : 4,
"0" : 1, 
 "1" : 2, 
 "2" : 4, 
 "3" : 5}]
}