{
"Class" : "org.joda.time.tz.ZoneInfoProvider", 
"Methods" : [{ "Name" : "<init>" ,
"Nodes" : 8,
"0" : [ 56,57 ]
"1" : [ 60 ]
"2" : [ 63 ]
"3" : [ 67,68,69,71,72 ]
"4" : [ 64 ]
"5" : [ 61 ]
"6" : [ 58 ]
"7" : [  ]
},{ "Name" : "<init>" ,
"Nodes" : 9,
"0" : [ 106,107 ]
"1" : [ 110 ]
"2" : [ 114,115,117 ]
"3" : [ 121,123,124 ]
"4" : [ 117 ]
"5" : [ 118 ]
"6" : [ 111 ]
"7" : [ 108 ]
"8" : [  ]
},{ "Name" : "getZone" ,
"Nodes" : 12,
"0" : [ 135 ]
"1" : [ 139,140 ]
"2" : [ 144 ]
"3" : [ 149 ]
"4" : [ 161 ]
"5" : [ 151,152,153 ]
"6" : [ 157 ]
"7" : [ 154 ]
"8" : [ 146 ]
"9" : [ 141 ]
"10" : [ 136 ]
"11" : [  ]
},{ "Name" : "openResource" ,
"Nodes" : 12,
"0" : [ 195 ]
"1" : [ 198,199 ]
"2" : [ 202 ]
"3" : [ 204 ]
"4" : [ 213 ]
"5" : [ 205 ]
"6" : [ 205 ]
"7" : [ 210,205 ]
"8" : [ 205 ]
"9" : [ 200 ]
"10" : [ 196 ]
"11" : [  ]
},{ "Name" : "loadZoneData" ,
"Nodes" : 4,
"0" : [ 225,226,227,228,235,223 ]
"1" : [ 239 ]
"2" : [ 236 ]
"3" : [  ]
},{ "Name" : "readZoneInfoMap" ,
"Nodes" : 8,
"0" : [ 273,274,275 ]
"1" : [ 275 ]
"2" : [ 280,281 ]
"3" : [ 281 ]
"4" : [ 288 ]
"5" : [ 281,283,286 ]
"6" : [ 275,276 ]
"7" : [  ]
}]
}