{
"Class" : "weka.classifiers.bayes.net.GUI$ActionZoomIn", 
"Methods" : [{ "Name" : "actionPerformed" ,
"Duas" : 69,
"0" :  "(1708,(1730,1731), this)",
"1" :  "(1708,(1730,1733), this)",
"2" :  "(1708,1733, this)",
"3" :  "(1708,1734, this)",
"4" :  "(1708,1736, this)",
"5" :  "(1708,1737, this)",
"6" :  "(1708,1738, this)",
"7" :  "(1708,1739, this)",
"8" :  "(1708,1740, this)",
"9" :  "(1708,1731, this)",
"10" :  "(1708,1727, this)",
"11" :  "(1708,1728, this)",
"12" :  "(1708,(1724,1725), this)",
"13" :  "(1708,(1724,1727), this)",
"14" :  "(1708,1725, this)",
"15" :  "(1708,1722, this)",
"16" :  "(1708,1718, this)",
"17" :  "(1708,(1730,1731), this.this$0)",
"18" :  "(1708,(1730,1733), this.this$0)",
"19" :  "(1708,1733, this.this$0)",
"20" :  "(1708,1734, this.this$0)",
"21" :  "(1708,1736, this.this$0)",
"22" :  "(1708,1737, this.this$0)",
"23" :  "(1708,1738, this.this$0)",
"24" :  "(1708,1739, this.this$0)",
"25" :  "(1708,1740, this.this$0)",
"26" :  "(1708,1731, this.this$0)",
"27" :  "(1708,1727, this.this$0)",
"28" :  "(1708,1728, this.this$0)",
"29" :  "(1708,(1724,1725), this.this$0)",
"30" :  "(1708,(1724,1727), this.this$0)",
"31" :  "(1708,1725, this.this$0)",
"32" :  "(1708,(1730,1731), this.a_zoomout)",
"33" :  "(1708,(1730,1733), this.a_zoomout)",
"34" :  "(1708,1731, this.a_zoomout)",
"35" :  "(1708,(1724,1725), this.a_zoomout)",
"36" :  "(1708,(1724,1727), this.a_zoomout)",
"37" :  "(1708,1725, this.a_zoomout)",
"38" :  "(1708,1733, this.m_jTfZoom)",
"39" :  "(1708,1727, this.m_jTfZoom)",
"40" :  "(1708,1737, this.m_GraphPanel)",
"41" :  "(1708,1738, this.m_GraphPanel)",
"42" :  "(1708,1739, this.m_jScrollPane)",
"43" :  "(1708,1740, this.m_jStatusBar)",
"44" :  "(1708,(1709,1710), s)",
"45" :  "(1708,(1709,1711), s)",
"46" :  "(1708,(1711,1712), s)",
"47" :  "(1708,(1711,1714), s)",
"48" :  "(1708,1714, s)",
"49" :  "(1708,(1717,1718), s)",
"50" :  "(1708,(1717,1720), s)",
"51" :  "(1708,(1720,1721), s)",
"52" :  "(1708,(1720,1730), s)",
"53" :  "(1708,(1724,1724), s)",
"54" :  "(1708,(1724,1727), s)",
"55" :  "(1708,1712, s)",
"56" :  "(1708,1710, s)",
"57" :  "(1710,(1721,1722), i)",
"58" :  "(1710,(1721,1724), i)",
"59" :  "(1710,1727, i)",
"60" :  "(1710,1728, i)",
"61" :  "(1712,(1721,1722), i)",
"62" :  "(1712,(1721,1724), i)",
"63" :  "(1712,1727, i)",
"64" :  "(1712,1728, i)",
"65" :  "(1714,(1721,1722), i)",
"66" :  "(1714,(1721,1724), i)",
"67" :  "(1714,1727, i)",
"68" :  "(1714,1728, i)"}]
}