{
"Class" : "weka.filters.unsupervised.attribute.NumericTransform", 
"Methods" : [{ "Name" : "setInputFormat" ,
"Duas" : 15,
"0" :  "(143,(143,144), this)",
"1" :  "(143,(143,146), this)",
"2" :  "(143,(146,147), this)",
"3" :  "(143,(146,149), this)",
"4" :  "(143,149, this)",
"5" :  "(143,150, this)",
"6" :  "(143,151, this)",
"7" :  "(143,149, instanceInfo)",
"8" :  "(143,150, instanceInfo)",
"9" :  "(143,151, instanceInfo)",
"10" :  "(143,(143,144), this.m_Class)",
"11" :  "(143,(143,146), this.m_Class)",
"12" :  "(143,(146,147), this.m_Method)",
"13" :  "(143,(146,149), this.m_Method)",
"14" :  "(143,150, this.m_Cols)"},{ "Name" : "input" ,
"Duas" : 77,
"0" :  "(168,(168,169), this)",
"1" :  "(168,(168,171), this)",
"2" :  "(168,(171,172), this)",
"3" :  "(168,(171,176), this)",
"4" :  "(168,176, this)",
"5" :  "(168,206, this)",
"6" :  "(168,(186,186), this)",
"7" :  "(168,(186,195), this)",
"8" :  "(168,172, this)",
"9" :  "(168,173, this)",
"10" :  "(168,179, instance)",
"11" :  "(168,(182,183), instance)",
"12" :  "(168,(182,199), instance)",
"13" :  "(168,(200,201), instance)",
"14" :  "(168,(200,203), instance)",
"15" :  "(168,203, instance)",
"16" :  "(168,205, instance)",
"17" :  "(168,201, instance)",
"18" :  "(168,(183,184), instance)",
"19" :  "(168,(183,186), instance)",
"20" :  "(168,195, instance)",
"21" :  "(168,(186,187), instance)",
"22" :  "(168,(186,195), instance)",
"23" :  "(168,187, instance)",
"24" :  "(168,(171,172), this.m_NewBatch)",
"25" :  "(168,(171,176), this.m_NewBatch)",
"26" :  "(168,176, TYPE)",
"27" :  "(168,176, this.m_Class)",
"28" :  "(168,176, this.m_Method)",
"29" :  "(168,(186,186), this.m_Cols)",
"30" :  "(168,(186,195), this.m_Cols)",
"31" :  "(176,188, m)",
"32" :  "(179,203, vals)",
"33" :  "(179,201, vals)",
"34" :  "(179,195, vals)",
"35" :  "(179,190, vals)",
"36" :  "(179,192, vals)",
"37" :  "(179,184, vals)",
"38" :  "(180,187, params)",
"39" :  "(180,188, params)",
"40" :  "(182,(182,183), i)",
"41" :  "(182,(182,199), i)",
"42" :  "(182,(183,184), i)",
"43" :  "(182,(183,186), i)",
"44" :  "(182,(186,186), i)",
"45" :  "(182,(186,195), i)",
"46" :  "(182,195, i)",
"47" :  "(182,182, i)",
"48" :  "(182,(186,187), i)",
"49" :  "(182,(186,195), i)",
"50" :  "(182,187, i)",
"51" :  "(182,190, i)",
"52" :  "(182,192, i)",
"53" :  "(182,184, i)",
"54" :  "(188,(189,189), newVal)",
"55" :  "(188,(189,190), newVal)",
"56" :  "(188,(189,190), newVal)",
"57" :  "(188,(189,192), newVal)",
"58" :  "(188,192, newVal)",
"59" :  "(182,(182,183), i)",
"60" :  "(182,(182,199), i)",
"61" :  "(182,(183,184), i)",
"62" :  "(182,(183,186), i)",
"63" :  "(182,(186,186), i)",
"64" :  "(182,(186,195), i)",
"65" :  "(182,195, i)",
"66" :  "(182,182, i)",
"67" :  "(182,(186,187), i)",
"68" :  "(182,(186,195), i)",
"69" :  "(182,187, i)",
"70" :  "(182,190, i)",
"71" :  "(182,192, i)",
"72" :  "(182,184, i)",
"73" :  "(201,205, inst)",
"74" :  "(201,206, inst)",
"75" :  "(203,205, inst)",
"76" :  "(203,206, inst)"},{ "Name" : "setOptions" ,
"Duas" : 13,
"0" :  "(275,(286,287), this)",
"1" :  "(275,(286,290), this)",
"2" :  "(275,287, this)",
"3" :  "(275,283, this)",
"4" :  "(275,279, this)",
"5" :  "(275,281, options)",
"6" :  "(275,290, options)",
"7" :  "(277,(278,279), classString)",
"8" :  "(277,(278,281), classString)",
"9" :  "(277,279, classString)",
"10" :  "(281,(282,283), methodString)",
"11" :  "(281,(282,286), methodString)",
"12" :  "(281,283, methodString)"},{ "Name" : "getOptions" ,
"Duas" : 23,
"0" :  "(301,(303,304), this)",
"1" :  "(301,(303,306), this)",
"2" :  "(301,(306,307), this)",
"3" :  "(301,(306,310), this)",
"4" :  "(301,(310,311), this)",
"5" :  "(301,(310,314), this)",
"6" :  "(301,(314,315), this)",
"7" :  "(301,(314,319), this)",
"8" :  "(301,316, this)",
"9" :  "(301,312, this)",
"10" :  "(301,308, this)",
"11" :  "(301,(310,311), this.m_Class)",
"12" :  "(301,(310,314), this.m_Class)",
"13" :  "(301,(314,315), this.m_Method)",
"14" :  "(301,(314,319), this.m_Method)",
"15" :  "(301,319, options)",
"16" :  "(301,315, options)",
"17" :  "(301,316, options)",
"18" :  "(301,311, options)",
"19" :  "(301,312, options)",
"20" :  "(301,307, options)",
"21" :  "(301,308, options)",
"22" :  "(301,304, options)"}]
}