{
"Class" : "org.apache.sysds.lops.Data", 
"Methods" : [{ "Name" : "<init>" ,
"Duas" : 62,
"0" :  "(72,74, this)",
"1" :  "(72,(77,78), this)",
"2" :  "(72,(77,82), this)",
"3" :  "(72,(83,84), this)",
"4" :  "(72,(83,86), this)",
"5" :  "(72,(86,86), this)",
"6" :  "(72,(86,87), this)",
"7" :  "(72,(87,87), this)",
"8" :  "(72,(87,87), this)",
"9" :  "(72,88, this)",
"10" :  "(72,103, this)",
"11" :  "(72,(105,106), this)",
"12" :  "(72,(105,120), this)",
"13" :  "(72,120, this)",
"14" :  "(72,121, this)",
"15" :  "(72,122, this)",
"16" :  "(72,115, this)",
"17" :  "(72,107, this)",
"18" :  "(72,108, this)",
"19" :  "(72,99, this)",
"20" :  "(72,100, this)",
"21" :  "(72,84, this)",
"22" :  "(72,(78,79), this)",
"23" :  "(72,(78,80), this)",
"24" :  "(72,80, this)",
"25" :  "(72,(98,99), op)",
"26" :  "(72,(98,103), op)",
"27" :  "(72,(98,98), input)",
"28" :  "(72,(98,103), input)",
"29" :  "(72,99, input)",
"30" :  "(72,100, input)",
"31" :  "(72,103, inputParametersLops)",
"32" :  "(72,106, inputParametersLops)",
"33" :  "(72,(110,110), inputParametersLops)",
"34" :  "(72,(110,120), inputParametersLops)",
"35" :  "(72,(111,113), inputParametersLops)",
"36" :  "(72,(111,120), inputParametersLops)",
"37" :  "(72,113, inputParametersLops)",
"38" :  "(72,(82,83), name)",
"39" :  "(72,(82,92), name)",
"40" :  "(72,88, name)",
"41" :  "(72,84, name)",
"42" :  "(72,(74,74), literal)",
"43" :  "(72,(74,74), literal)",
"44" :  "(72,80, literal)",
"45" :  "(72,120, fmt)",
"46" :  "(72,121, fmt)",
"47" :  "(72,(86,86), FUNCTIONOUTPUT)",
"48" :  "(72,(86,87), FUNCTIONOUTPUT)",
"49" :  "(72,121, this.outParams)",
"50" :  "(73,(83,84), this._op)",
"51" :  "(73,(83,86), this._op)",
"52" :  "(73,(86,86), this._op)",
"53" :  "(73,(86,87), this._op)",
"54" :  "(73,(87,87), this._op)",
"55" :  "(73,(87,87), this._op)",
"56" :  "(73,(78,79), this._op)",
"57" :  "(73,(78,80), this._op)",
"58" :  "(74,(77,78), this.literal_var)",
"59" :  "(74,(77,82), this.literal_var)",
"60" :  "(103,(105,106), this._inputParams)",
"61" :  "(103,(105,120), this._inputParams)"},{ "Name" : "getNamedInputLop" ,
"Duas" : 11,
"0" :  "(178,(178,179), this)",
"1" :  "(178,(178,181), this)",
"2" :  "(178,179, this)",
"3" :  "(178,(178,179), name)",
"4" :  "(178,(178,181), name)",
"5" :  "(178,179, name)",
"6" :  "(178,181, defaultVal)",
"7" :  "(178,(178,179), this._inputParams)",
"8" :  "(178,(178,181), this._inputParams)",
"9" :  "(178,179, this._inputParams)",
"10" :  "(178,181, STRING)"},{ "Name" : "getBooleanValue" ,
"Duas" : 5,
"0" :  "(193,(193,194), this)",
"1" :  "(193,(193,197), this)",
"2" :  "(193,194, this)",
"3" :  "(193,(193,194), this.literal_var)",
"4" :  "(193,(193,197), this.literal_var)"},{ "Name" : "getDoubleValue" ,
"Duas" : 5,
"0" :  "(201,(201,202), this)",
"1" :  "(201,(201,205), this)",
"2" :  "(201,202, this)",
"3" :  "(201,(201,202), this.literal_var)",
"4" :  "(201,(201,205), this.literal_var)"},{ "Name" : "getLongValue" ,
"Duas" : 14,
"0" :  "(209,(209,210), this)",
"1" :  "(209,(209,222), this)",
"2" :  "(209,210, this)",
"3" :  "(209,215, this)",
"4" :  "(209,213, this)",
"5" :  "(209,(209,210), this.literal_var)",
"6" :  "(209,(209,222), this.literal_var)",
"7" :  "(209,(211,218), $SwitchMap$org$apache$sysds$common$Types$ValueType)",
"8" :  "(209,(211,213), $SwitchMap$org$apache$sysds$common$Types$ValueType)",
"9" :  "(209,(211,215), $SwitchMap$org$apache$sysds$common$Types$ValueType)",
"10" :  "(210,(211,218), vt)",
"11" :  "(210,(211,213), vt)",
"12" :  "(210,(211,215), vt)",
"13" :  "(210,218, vt)"},{ "Name" : "getStringValue" ,
"Duas" : 5,
"0" :  "(226,(226,227), this)",
"1" :  "(226,(226,230), this)",
"2" :  "(226,227, this)",
"3" :  "(226,(226,227), this.literal_var)",
"4" :  "(226,(226,230), this.literal_var)"},{ "Name" : "isPersistentWrite" ,
"Duas" : 6,
"0" :  "(234,(234,234), this)",
"1" :  "(234,(234,234), this)",
"2" :  "(234,(234,234), PERSISTENTWRITE)",
"3" :  "(234,(234,234), PERSISTENTWRITE)",
"4" :  "(234,(234,234), this._op)",
"5" :  "(234,(234,234), this._op)"},{ "Name" : "isPersistentRead" ,
"Duas" : 10,
"0" :  "(238,(238,238), this)",
"1" :  "(238,(238,238), this)",
"2" :  "(238,(238,238), this)",
"3" :  "(238,(238,238), this)",
"4" :  "(238,(238,238), PERSISTENTREAD)",
"5" :  "(238,(238,238), PERSISTENTREAD)",
"6" :  "(238,(238,238), this._op)",
"7" :  "(238,(238,238), this._op)",
"8" :  "(238,(238,238), this.literal_var)",
"9" :  "(238,(238,238), this.literal_var)"},{ "Name" : "getInstructions" ,
"Duas" : 172,
"0" :  "(249,(249,249), this)",
"1" :  "(249,(249,252), this)",
"2" :  "(249,(253,254), this)",
"3" :  "(249,(253,256), this)",
"4" :  "(249,(258,259), this)",
"5" :  "(249,(258,263), this)",
"6" :  "(249,(263,264), this)",
"7" :  "(249,(263,269), this)",
"8" :  "(249,269, this)",
"9" :  "(249,266, this)",
"10" :  "(249,272, this)",
"11" :  "(249,274, this)",
"12" :  "(249,277, this)",
"13" :  "(249,(278,279), this)",
"14" :  "(249,(278,368), this)",
"15" :  "(249,(368,369), this)",
"16" :  "(249,(368,382), this)",
"17" :  "(249,370, this)",
"18" :  "(249,376, this)",
"19" :  "(249,373, this)",
"20" :  "(249,(281,281), this)",
"21" :  "(249,(281,282), this)",
"22" :  "(249,286, this)",
"23" :  "(249,352, this)",
"24" :  "(249,(360,361), this)",
"25" :  "(249,(360,368), this)",
"26" :  "(249,355, this)",
"27" :  "(249,321, this)",
"28" :  "(249,322, this)",
"29" :  "(249,323, this)",
"30" :  "(249,(345,346), this)",
"31" :  "(249,(345,351), this)",
"32" :  "(249,334, this)",
"33" :  "(249,331, this)",
"34" :  "(249,327, this)",
"35" :  "(249,289, this)",
"36" :  "(249,290, this)",
"37" :  "(249,291, this)",
"38" :  "(249,(313,315), this)",
"39" :  "(249,(313,320), this)",
"40" :  "(249,302, this)",
"41" :  "(249,298, this)",
"42" :  "(249,294, this)",
"43" :  "(249,(281,282), this)",
"44" :  "(249,(281,284), this)",
"45" :  "(249,261, this)",
"46" :  "(249,(249,250), this)",
"47" :  "(249,(249,252), this)",
"48" :  "(249,250, this)",
"49" :  "(249,266, input1)",
"50" :  "(249,261, input1)",
"51" :  "(249,274, input2)",
"52" :  "(249,(258,259), this._op)",
"53" :  "(249,(258,263), this._op)",
"54" :  "(249,(263,264), this._op)",
"55" :  "(249,(263,269), this._op)",
"56" :  "(249,269, this._op)",
"57" :  "(249,(278,279), this._op)",
"58" :  "(249,(278,368), this._op)",
"59" :  "(249,(368,369), this._op)",
"60" :  "(249,(368,382), this._op)",
"61" :  "(249,(249,250), this._op)",
"62" :  "(249,(249,252), this._op)",
"63" :  "(249,(253,254), SPARK)",
"64" :  "(249,(253,256), SPARK)",
"65" :  "(249,(360,361), SPARK)",
"66" :  "(249,(360,368), SPARK)",
"67" :  "(249,(345,346), SPARK)",
"68" :  "(249,(345,351), SPARK)",
"69" :  "(249,(313,315), SPARK)",
"70" :  "(249,(313,320), SPARK)",
"71" :  "(249,272, this._inputParams)",
"72" :  "(249,274, SCALAR)",
"73" :  "(249,376, SCALAR)",
"74" :  "(249,373, SCALAR)",
"75" :  "(249,286, SCALAR)",
"76" :  "(249,274, STRING)",
"77" :  "(249,376, STRING)",
"78" :  "(249,373, STRING)",
"79" :  "(249,286, STRING)",
"80" :  "(249,(281,281), MATRIX)",
"81" :  "(249,(281,282), MATRIX)",
"82" :  "(249,(281,282), FRAME)",
"83" :  "(249,(281,284), FRAME)",
"84" :  "(249,284, TEXT)",
"85" :  "(249,(288,289), CSV)",
"86" :  "(249,(288,320), CSV)",
"87" :  "(249,(320,321), LIBSVM)",
"88" :  "(249,(320,351), LIBSVM)",
"89" :  "(249,(351,352), HDF5)",
"90" :  "(249,(351,368), HDF5)",
"91" :  "(252,256, sb)",
"92" :  "(252,257, sb)",
"93" :  "(252,264, sb)",
"94" :  "(252,265, sb)",
"95" :  "(252,266, sb)",
"96" :  "(252,271, sb)",
"97" :  "(252,274, sb)",
"98" :  "(252,382, sb)",
"99" :  "(252,369, sb)",
"100" :  "(252,376, sb)",
"101" :  "(252,378, sb)",
"102" :  "(252,379, sb)",
"103" :  "(252,373, sb)",
"104" :  "(252,279, sb)",
"105" :  "(252,286, sb)",
"106" :  "(252,357, sb)",
"107" :  "(252,358, sb)",
"108" :  "(252,361, sb)",
"109" :  "(252,362, sb)",
"110" :  "(252,338, sb)",
"111" :  "(252,339, sb)",
"112" :  "(252,340, sb)",
"113" :  "(252,341, sb)",
"114" :  "(252,342, sb)",
"115" :  "(252,343, sb)",
"116" :  "(252,346, sb)",
"117" :  "(252,347, sb)",
"118" :  "(252,306, sb)",
"119" :  "(252,307, sb)",
"120" :  "(252,308, sb)",
"121" :  "(252,309, sb)",
"122" :  "(252,310, sb)",
"123" :  "(252,311, sb)",
"124" :  "(252,315, sb)",
"125" :  "(252,316, sb)",
"126" :  "(252,259, sb)",
"127" :  "(252,260, sb)",
"128" :  "(252,261, sb)",
"129" :  "(252,254, sb)",
"130" :  "(272,(273,273), fnameLop)",
"131" :  "(272,(273,273), fnameLop)",
"132" :  "(272,(273,273), fnameLop)",
"133" :  "(272,(273,273), fnameLop)",
"134" :  "(277,379, oparams)",
"135" :  "(277,282, oparams)",
"136" :  "(277,(288,289), oparams)",
"137" :  "(277,(288,320), oparams)",
"138" :  "(277,(320,321), oparams)",
"139" :  "(277,(320,351), oparams)",
"140" :  "(277,(351,352), oparams)",
"141" :  "(277,(351,368), oparams)",
"142" :  "(282,286, fmt)",
"143" :  "(284,286, fmt)",
"144" :  "(289,(293,294), headerLop)",
"145" :  "(289,(293,297), headerLop)",
"146" :  "(289,307, headerLop)",
"147" :  "(290,(297,298), delimLop)",
"148" :  "(290,(297,301), delimLop)",
"149" :  "(290,309, delimLop)",
"150" :  "(291,(301,302), sparseLop)",
"151" :  "(291,(301,306), sparseLop)",
"152" :  "(291,311, sparseLop)",
"153" :  "(321,(325,326), delimLop)",
"154" :  "(321,(325,329), delimLop)",
"155" :  "(321,339, delimLop)",
"156" :  "(322,(329,330), indexDelimLop)",
"157" :  "(322,(329,333), indexDelimLop)",
"158" :  "(322,341, indexDelimLop)",
"159" :  "(323,(333,334), sparseLop)",
"160" :  "(323,(333,338), sparseLop)",
"161" :  "(323,343, sparseLop)",
"162" :  "(352,(353,354), datasetNameLop)",
"163" :  "(352,(353,357), datasetNameLop)",
"164" :  "(352,358, datasetNameLop)",
"165" :  "(370,(371,372), descriptionLop)",
"166" :  "(370,(371,376), descriptionLop)",
"167" :  "(370,(372,372), descriptionLop)",
"168" :  "(370,(372,372), descriptionLop)",
"169" :  "(370,373, descriptionLop)",
"170" :  "(370,(372,372), descriptionLop)",
"171" :  "(370,(372,372), descriptionLop)"},{ "Name" : "getCreateVarInstructions" ,
"Duas" : 52,
"0" :  "(400,(400,400), this)",
"1" :  "(400,(400,402), this)",
"2" :  "(400,(402,403), this)",
"3" :  "(400,(402,405), this)",
"4" :  "(400,405, this)",
"5" :  "(400,418, this)",
"6" :  "(400,(450,451), this)",
"7" :  "(400,(450,455), this)",
"8" :  "(400,451, this)",
"9" :  "(400,446, this)",
"10" :  "(400,440, this)",
"11" :  "(400,435, this)",
"12" :  "(400,(400,400), this)",
"13" :  "(400,(400,402), this)",
"14" :  "(400,(400,402), this)",
"15" :  "(400,(400,458), this)",
"16" :  "(400,458, this)",
"17" :  "(400,414, outputFileName)",
"18" :  "(400,412, outputLabel)",
"19" :  "(400,(400,400), MATRIX)",
"20" :  "(400,(400,402), MATRIX)",
"21" :  "(400,(450,451), FRAME)",
"22" :  "(400,(450,455), FRAME)",
"23" :  "(400,(400,400), FRAME)",
"24" :  "(400,(400,402), FRAME)",
"25" :  "(400,(400,402), LIST)",
"26" :  "(400,(400,458), LIST)",
"27" :  "(400,(402,403), this._op)",
"28" :  "(400,(402,405), this._op)",
"29" :  "(400,(433,434), CSV)",
"30" :  "(400,(433,438), CSV)",
"31" :  "(400,(438,439), LIBSVM)",
"32" :  "(400,(438,444), LIBSVM)",
"33" :  "(400,(444,445), HDF5)",
"34" :  "(400,(444,450), HDF5)",
"35" :  "(405,(433,434), oparams)",
"36" :  "(405,(433,438), oparams)",
"37" :  "(405,(438,439), oparams)",
"38" :  "(405,(438,444), oparams)",
"39" :  "(405,(444,445), oparams)",
"40" :  "(405,(444,450), oparams)",
"41" :  "(407,455, sb)",
"42" :  "(407,452, sb)",
"43" :  "(407,453, sb)",
"44" :  "(407,445, sb)",
"45" :  "(407,446, sb)",
"46" :  "(407,439, sb)",
"47" :  "(407,440, sb)",
"48" :  "(407,434, sb)",
"49" :  "(407,435, sb)",
"50" :  "(451,(453,453), schema)",
"51" :  "(451,(453,453), schema)"},{ "Name" : "createVarCSVHelper" ,
"Duas" : 49,
"0" :  "(469,(470,471), this)",
"1" :  "(469,(470,499), this)",
"2" :  "(469,499, this)",
"3" :  "(469,500, this)",
"4" :  "(469,501, this)",
"5" :  "(469,512, this)",
"6" :  "(469,508, this)",
"7" :  "(469,504, this)",
"8" :  "(469,471, this)",
"9" :  "(469,472, this)",
"10" :  "(469,473, this)",
"11" :  "(469,474, this)",
"12" :  "(469,475, this)",
"13" :  "(469,(470,471), this._op)",
"14" :  "(469,(470,499), this._op)",
"15" :  "(469,516, sb)",
"16" :  "(469,517, sb)",
"17" :  "(469,518, sb)",
"18" :  "(469,519, sb)",
"19" :  "(469,520, sb)",
"20" :  "(469,522, sb)",
"21" :  "(469,477, sb)",
"22" :  "(469,478, sb)",
"23" :  "(469,479, sb)",
"24" :  "(469,480, sb)",
"25" :  "(469,481, sb)",
"26" :  "(469,482, sb)",
"27" :  "(469,483, sb)",
"28" :  "(469,485, sb)",
"29" :  "(469,494, sb)",
"30" :  "(469,489, sb)",
"31" :  "(469,490, sb)",
"32" :  "(475,(484,485), naLop)",
"33" :  "(475,(484,497), naLop)",
"34" :  "(475,(486,487), naLop)",
"35" :  "(475,(486,492), naLop)",
"36" :  "(475,(492,494), naLop)",
"37" :  "(475,(492,497), naLop)",
"38" :  "(475,494, naLop)",
"39" :  "(475,487, naLop)",
"40" :  "(499,(503,504), headerLop)",
"41" :  "(499,(503,507), headerLop)",
"42" :  "(499,516, headerLop)",
"43" :  "(500,(507,508), delimLop)",
"44" :  "(500,(507,511), delimLop)",
"45" :  "(500,518, delimLop)",
"46" :  "(501,(511,512), sparseLop)",
"47" :  "(501,(511,516), sparseLop)",
"48" :  "(501,520, sparseLop)"},{ "Name" : "createVarLIBSVMHelper" ,
"Duas" : 31,
"0" :  "(526,(527,528), this)",
"1" :  "(526,(527,537), this)",
"2" :  "(526,537, this)",
"3" :  "(526,538, this)",
"4" :  "(526,539, this)",
"5" :  "(526,550, this)",
"6" :  "(526,547, this)",
"7" :  "(526,543, this)",
"8" :  "(526,528, this)",
"9" :  "(526,529, this)",
"10" :  "(526,(527,528), this._op)",
"11" :  "(526,(527,537), this._op)",
"12" :  "(526,554, sb)",
"13" :  "(526,555, sb)",
"14" :  "(526,556, sb)",
"15" :  "(526,557, sb)",
"16" :  "(526,558, sb)",
"17" :  "(526,560, sb)",
"18" :  "(526,531, sb)",
"19" :  "(526,532, sb)",
"20" :  "(526,533, sb)",
"21" :  "(526,534, sb)",
"22" :  "(537,(541,542), delimLop)",
"23" :  "(537,(541,545), delimLop)",
"24" :  "(537,554, delimLop)",
"25" :  "(538,(545,546), indexDelimLop)",
"26" :  "(538,(545,549), indexDelimLop)",
"27" :  "(538,556, indexDelimLop)",
"28" :  "(539,(549,550), sparseLop)",
"29" :  "(539,(549,554), sparseLop)",
"30" :  "(539,558, sparseLop)"},{ "Name" : "createVarHDF5Helper" ,
"Duas" : 15,
"0" :  "(564,(565,566), this)",
"1" :  "(564,(565,571), this)",
"2" :  "(564,571, this)",
"3" :  "(564,574, this)",
"4" :  "(564,566, this)",
"5" :  "(564,(565,566), this._op)",
"6" :  "(564,(565,571), this._op)",
"7" :  "(564,576, sb)",
"8" :  "(564,577, sb)",
"9" :  "(564,579, sb)",
"10" :  "(564,567, sb)",
"11" :  "(564,568, sb)",
"12" :  "(571,(572,573), datasetNameLop)",
"13" :  "(571,(572,576), datasetNameLop)",
"14" :  "(571,576, datasetNameLop)"}]
}