{
"Class" : "org.apache.sysds.runtime.instructions.gpu.AggregateUnaryGPUInstruction", 
"Methods" : [{ "Name" : "parseInstruction" ,
"Duas" : 11,
"0" :  "(46,60, str)",
"1" :  "(47,(54,54), opcode)",
"2" :  "(47,(54,55), opcode)",
"3" :  "(47,(54,54), opcode)",
"4" :  "(47,(54,55), opcode)",
"5" :  "(47,(54,55), opcode)",
"6" :  "(47,(54,58), opcode)",
"7" :  "(47,58, opcode)",
"8" :  "(47,60, opcode)",
"9" :  "(48,60, in1)",
"10" :  "(49,60, out)"},{ "Name" : "processInstruction" ,
"Duas" : 38,
"0" :  "(65,75, this)",
"1" :  "(65,80, this)",
"2" :  "(65,88, this)",
"3" :  "(65,92, this)",
"4" :  "(65,100, this)",
"5" :  "(65,85, this)",
"6" :  "(65,82, this)",
"7" :  "(65,75, ec)",
"8" :  "(65,88, ec)",
"9" :  "(65,92, ec)",
"10" :  "(65,100, ec)",
"11" :  "(65,85, ec)",
"12" :  "(65,82, ec)",
"13" :  "(65,75, this._input1)",
"14" :  "(65,92, this._input1)",
"15" :  "(65,80, this._optr)",
"16" :  "(65,88, this._optr)",
"17" :  "(65,88, this._output)",
"18" :  "(65,100, this._output)",
"19" :  "(65,85, this._output)",
"20" :  "(65,82, this._output)",
"21" :  "(67,(70,70), opcode)",
"22" :  "(67,(70,71), opcode)",
"23" :  "(67,(70,70), opcode)",
"24" :  "(67,(70,71), opcode)",
"25" :  "(67,(70,71), opcode)",
"26" :  "(67,(70,75), opcode)",
"27" :  "(75,88, in1)",
"28" :  "(77,85, rlen)",
"29" :  "(78,82, clen)",
"30" :  "(80,(81,82), indexFunction)",
"31" :  "(80,(81,84), indexFunction)",
"32" :  "(80,(84,85), indexFunction)",
"33" :  "(80,(84,88), indexFunction)",
"34" :  "(80,(99,99), indexFunction)",
"35" :  "(80,(99,100), indexFunction)",
"36" :  "(80,(99,100), indexFunction)",
"37" :  "(80,(99,102), indexFunction)"}]
}