{
"Class" : "org.joda.time.tz.FixedDateTimeZone", 
"Methods" : [{ "Name" : "toTimeZone" ,
"Edges" : 8,
"Duas" : 9,
"3" : 3, 
 "4" : 4, 
 "5" : 0, 
 "6" : 1, 
 "7" : 5, 
 "8" : 6},{ "Name" : "equals" ,
"Edges" : 15,
"Duas" : 27,
"0" : 9, 
 "1" : 10, 
 "2" : 13, 
 "3" : 14, 
 "4" : 11, 
 "5" : 12, 
 "6" : 2, 
 "7" : 3, 
 "8" : 9, 
 "9" : 10, 
 "10" : 4, 
 "11" : 5, 
 "13" : 11, 
 "14" : 12, 
 "15" : 2, 
 "16" : 3, 
 "17" : 13, 
 "18" : 14, 
 "19" : 11, 
 "20" : 12, 
 "21" : 2, 
 "22" : 3, 
 "23" : 11, 
 "24" : 12, 
 "25" : 2, 
 "26" : 3}]
}