{
"Class" : "org.apache.commons.compress.archivers.cpio.CpioUtil", 
"Methods" : [{ "Name" : "byteArray2long" ,
"Edges" : 14,
"Duas" : 33,
"0" : 5, 
 "1" : 6, 
 "2" : 0, 
 "3" : 1, 
 "5" : 10, 
 "6" : 11, 
 "8" : 12, 
 "9" : 13, 
 "13" : 12, 
 "14" : 13, 
 "17" : 12, 
 "18" : 13, 
 "23" : 10, 
 "24" : 11, 
 "29" : 10, 
 "30" : 11},{ "Name" : "long2byteArray" ,
"Edges" : 16,
"Duas" : 35,
"1" : 0, 
 "2" : 1, 
 "3" : 5, 
 "4" : 6, 
 "6" : 2, 
 "7" : 3, 
 "8" : 12, 
 "9" : 13, 
 "17" : 10, 
 "18" : 11, 
 "23" : 10, 
 "24" : 11, 
 "27" : 2, 
 "28" : 3, 
 "31" : 2, 
 "32" : 3}]
}