{
"Class" : "org.jfree.data.time.TimeSeriesTableModel", 
"Methods" : [{ "Name" : "getColumnClass" ,
"Nodes" : 12,
"0" : [ 116 ]
"1" : [ 120 ]
"2" : [ 124 ]
"3" : [ 121 ]
"4" : [ 121 ]
"5" : [ 121 ]
"6" : [ 121 ]
"7" : [ 117 ]
"8" : [ 117 ]
"9" : [ 117 ]
"10" : [ 117 ]
"11" : [  ]
},{ "Name" : "getColumnName" ,
"Nodes" : 6,
"0" : [ 138 ]
"1" : [ 142 ]
"2" : [ 146 ]
"3" : [ 143 ]
"4" : [ 139 ]
"5" : [  ]
},{ "Name" : "getValueAt" ,
"Nodes" : 12,
"0" : [ 171 ]
"1" : [ 185 ]
"2" : [ 189 ]
"3" : [ 193 ]
"4" : [ 190 ]
"5" : [ 186 ]
"6" : [ 172 ]
"7" : [ 176 ]
"8" : [ 180 ]
"9" : [ 177 ]
"10" : [ 173 ]
"11" : [  ]
},{ "Name" : "isCellEditable" ,
"Nodes" : 7,
"0" : [ 209 ]
"1" : [ 218 ]
"2" : [ 210 ]
"3" : [ 211 ]
"4" : [ 210 ]
"5" : [ 214 ]
"6" : [  ]
},{ "Name" : "setValueAt" ,
"Nodes" : 9,
"0" : [ 231 ]
"1" : [ 246 ]
"2" : [ 250 ]
"3" : [ 254 ]
"4" : [ 251 ]
"5" : [ 248 ]
"6" : [ 234 ]
"7" : [ 242,236,237 ]
"8" : [  ]
}]
}