{
"Class" : "org.apache.commons.math3.optimization.fitting.GaussianFitter$ParameterGuesser", 
"Methods" : [{ "Name" : "<init>" ,
"Edges" : 7,
"5" : [ 5, 11],
"6" : [ 6],
"3" : [ 6, 7, 10],
"4" : [ 0, 1, 2, 3, 4, 6, 8, 9],
"0" : [ 0, 1, 2, 3, 4, 6, 8, 9],
"1" : [ 6, 7, 10],
"2" : [ 5, 11],
"CoveredDUAsByEdges" : 12,
"Duas" : 12
},{ "Name" : "findMaxY" ,
"Edges" : 8,
"0" : [ ],
"6" : [ 0, 7],
"7" : [ 1],
"1" : [ 1],
"3" : [ 0, 2, 5, 7],
"4" : [ 0, 3, 7, 11],
"2" : [ 0, 2, 5, 7, 11],
"5" : [ 0, 7, 11],
"CoveredDUAsByEdges" : 7,
"Duas" : 22
},{ "Name" : "interpolateXAtY" ,
"Edges" : 10,
"6" : [ 3],
"7" : [ 0, 1, 2, 4, 5, 6],
"4" : [ 0, 1, 2, 4, 5, 6, 7, 12, 15],
"5" : [ 0, 1, 2, 4, 5, 6, 8, 13],
"1" : [ 0, 16, 1, 2, 19, 4, 5, 6, 8, 9, 13],
"2" : [ 0, 1, 2, 4, 5, 6, 8, 10, 11, 13, 14, 17, 18],
"3" : [ 0, 1, 2, 4, 5, 6, 8, 10, 11, 13, 14, 17, 18],
"8" : [ 0, 1, 2, 4, 5, 6, 8, 9, 13, 16, 19],
"9" : [ 0, 1, 2, 4, 5, 6, 7, 12, 15],
"0" : [ 3],
"CoveredDUAsByEdges" : 20,
"Duas" : 20
},{ "Name" : "getInterpolationPointsForY" ,
"Edges" : 19,
"13" : [ 7],
"14" : [ 6, 8],
"10" : [ 6, 8],
"17" : [ 6, 8, 9],
"18" : [ 6, 8, 10],
"2" : [ 2, 4, 5, 6, 8, 24, 25, 11, 13],
"3" : [ 3, 19, 6, 8, 12],
"11" : [ 17, 6, 8, 9],
"12" : [ 18, 19, 6, 8],
"1" : [ 19, 6, 8],
"16" : [ 17, 4, 5, 6, 8, 24, 9, 25, 13],
"8" : [ 0, 33, 4, 20, 5, 6, 8, 24, 25, 13, 29],
"9" : [ 1, 34, 4, 5, 6, 8, 13, 14, 21, 24, 25, 26, 30],
"0" : [ 1, 34, 4, 5, 6, 8, 13, 14, 21, 24, 25, 26, 30],
"4" : [ 0, 32, 33, 4, 36, 5, 6, 8, 13, 15, 20, 24, 25, 29],
"5" : [ 0, 33, 35, 4, 5, 6, 8, 13, 16, 20, 24, 25, 29, 31],
"6" : [ 0, 33, 35, 4, 5, 6, 8, 13, 16, 20, 24, 25, 29, 31],
"7" : [ 0, 32, 33, 4, 36, 5, 6, 8, 13, 15, 20, 24, 25, 29],
"15" : [ 7],
"CoveredDUAsByEdges" : 33,
"Duas" : 44
},{ "Name" : "isBetween" ,
"Edges" : 11,
"3" : [ 0, 8],
"4" : [ 1, 9],
"9" : [ 6, 14],
"10" : [ 7, 15],
"6" : [ 2, 12],
"7" : [ 3, 13],
"1" : [ 4, 10],
"2" : [ 5, 11],
"8" : [ ],
"5" : [ ],
"0" : [ ],
"CoveredDUAsByEdges" : 16,
"Duas" : 16
}]
}